graphal/__init__.py
graphal/algorithm.py
graphal-1.0.1.dist-info/LICENSE
graphal-1.0.1.dist-info/METADATA
graphal-1.0.1.dist-info/WHEEL
graphal-1.0.1.dist-info/top_level.txt
graphal-1.0.1.dist-info/RECORD
