Metadata-Version: 2.1
Name: graphal
Version: 1.0.1
Summary: Graphs & Algorithms
Author: graphal
Keywords: graphal python
Classifier: Programming Language :: Python :: 3.11
Classifier: License :: OSI Approved :: MIT License
Classifier: Operating System :: OS Independent
Requires-Python: >=3.7
License-File: LICENSE
Requires-Dist: requests (>=2.25.1)
